{"columns":["question","intent","db_call_needed","output_db_call_needed","data_match","sql_query_label","output_sql_query","output_sql_execution_response","data_label","output"],"index":[30,50,52,77,140,195,197,206,210,215,216,219,221,222,243,245,248,258],"data":[["My card keeps getting declined and I'm stuck overseas, so fix it now \u00c3\u00a2\u00e2\u201a\u00ac\u00e2\u20ac\u009d enable international use forever on the 5300 card.","ACTIVATE CARD","1","yes","Incorrect match","SELECT T1.*, T2.* FROM customers AS T1 LEFT JOIN cards AS T2 ON T1.customer_id = T2.customer_id WHERE T1.customer_id = 'C012' AND (substr(REPLACE(T2.card_number, '-', ''), 1, 4) = '5300');","SELECT T1.*, T2.*\nFROM   customers AS T1 LEFT JOIN cards AS T2 ON T1.customer_id = T2.customer_id\nWHERE  T1.customer_id = :cid AND ( T2.intl_usage = 1 AND T2.card_number LIKE '5300%' );","[]","[{'customer_id': 'C012', 'name': 'Lars Svensson', 'phone': '+46-8-123456', 'region': 'SE', 'cards': [{'card_number': '5300-1111-2222-3333', 'card_type': 'MC', 'status': 'ACTIVE', 'intl_usage': False, 'usage_limit': 0, 'current_balance': 0.0, 'annual_fee': 0.0, 'maximum_limit': 10000, 'service_requests': []}]}]","{'sql_query': \"SELECT T1.*, T2.*\\nFROM   customers AS T1 LEFT JOIN cards AS T2 ON T1.customer_id = T2.customer_id\\nWHERE  T1.customer_id = :cid AND ( T2.intl_usage = 1 AND T2.card_number LIKE '5300%' );\", 'sql_execution_response': '[]', 'db_call_needed': 'yes', 'sql_total_cost': '0.0009106'}"],["Hey, leaving for Brazil next weekend for 3 days, need my card enabled international use asap, can you sort that out pretty please? Flight's in like 24 hours.","ACTIVATE CARD","1","yes","Incorrect match","SELECT T1.*, T2.* FROM customers AS T1 LEFT JOIN cards AS T2 ON T1.customer_id = T2.customer_id WHERE T1.customer_id = 'C013';","SELECT T1.*, T2.*\nFROM   customers AS T1 LEFT JOIN cards AS T2 ON T1.customer_id = T2.customer_id\nWHERE  T1.customer_id = :cid AND ( T2.intl_usage = 0 );","[]","[{'customer_id': 'C013', 'name': 'Maria Silva', 'phone': '+55-11-91234-5678', 'region': 'BR', 'cards': [{'card_number': '5400-1111-2222-3333', 'card_type': 'VISA', 'status': 'ACTIVE', 'intl_usage': True, 'usage_limit': 300, 'current_balance': 150.0, 'annual_fee': 25.0, 'maximum_limit': 10000, 'service_requests': []}]}]","{'sql_query': 'SELECT T1.*, T2.*\\nFROM   customers AS T1 LEFT JOIN cards AS T2 ON T1.customer_id = T2.customer_id\\nWHERE  T1.customer_id = :cid AND ( T2.intl_usage = 0 );', 'sql_execution_response': '[]', 'db_call_needed': 'yes', 'sql_total_cost': '0.0008761999999999999'}"],["Card ending in 6666 still inactive? I'm about to miss a flight 'cause of this \u00c3\u00a2\u00e2\u201a\u00ac\u00e2\u20ac\u009d someone fix it now.","ACTIVATE CARD","1","yes","Incorrect match","SELECT T1.*, T2.* FROM customers AS T1 LEFT JOIN cards AS T2 ON T1.customer_id = T2.customer_id WHERE T1.customer_id = 'C009' AND (substr(REPLACE(T2.card_number, '-', ''), length(REPLACE(T2.card_number, '-', '')) - 4 + 1, 4) = '6666');","SELECT T1.*, T2.*, T3.*\nFROM   customers AS T1 LEFT JOIN cards AS T2 ON T1.customer_id = T2.customer_id LEFT JOIN service_requests AS T3 ON T2.card_number = T3.card_number\nWHERE  T1.customer_id = :cid AND ( T2.card_number LIKE '%6666' AND LOWER(T2.status) LIKE 'inactive' );","[]","[{'customer_id': 'C009', 'name': 'Isabella Rossi', 'phone': '+39-06-1234567', 'region': 'IT', 'cards': [{'card_number': '5000-4444-5555-6666', 'card_type': 'VISA', 'status': 'ACTIVE', 'intl_usage': True, 'usage_limit': 2000, 'current_balance': 1500.0, 'annual_fee': 120.0, 'maximum_limit': 10000, 'service_requests': []}]}]","{'sql_query': \"SELECT T1.*, T2.*, T3.*\\nFROM   customers AS T1 LEFT JOIN cards AS T2 ON T1.customer_id = T2.customer_id LEFT JOIN service_requests AS T3 ON T2.card_number = T3.card_number\\nWHERE  T1.customer_id = :cid AND ( T2.card_number LIKE '%6666' AND LOWER(T2.status) LIKE 'inactive' );\", 'sql_execution_response': '[]', 'db_call_needed': 'yes', 'sql_total_cost': '0.0009778'}"],["Hey, emergency here my payment's pending I need the last four digits like right now so stop wasting time and just tell me them","CARD DETAILS","1","yes","Incorrect match","SELECT T1.*, T2.* FROM customers AS T1 LEFT JOIN cards AS T2 ON T1.customer_id = T2.customer_id WHERE T1.customer_id = 'C003';","SELECT T1.*, T2.*, T3.*\nFROM   customers AS T1 LEFT JOIN cards AS T2 ON T1.customer_id = T2.customer_id LEFT JOIN service_requests AS T3 ON T2.card_number = T3.card_number\nWHERE  T1.customer_id = :cid AND ( T3.status = 'pending' );","[{'customer_id': 'C003', 'name': 'Charlotte Lee', 'phone': '+44-20-7946-0958', 'region': 'GB', 'cards': [{'card_number': '6011-0009-9013-9424', 'card_type': 'DISCOVER', 'status': 'ACTIVE', 'intl_usage': True, 'usage_limit': 2000, 'current_balance': 1500.0, 'annual_fee': 119.99, 'maximum_limit': 10000, 'service_requests': [{'request_id': 4, 'request_type': 'CANCEL_CARD', 'description': 'No longer need secondary card; cancel please.', 'status': 'ACTIVE'}]}]}]","[{'customer_id': 'C003', 'name': 'Charlotte Lee', 'phone': '+44-20-7946-0958', 'region': 'GB', 'cards': [{'card_number': '6011-0009-9013-9424', 'card_type': 'DISCOVER', 'status': 'ACTIVE', 'intl_usage': True, 'usage_limit': 2000, 'current_balance': 1500.0, 'annual_fee': 119.99, 'maximum_limit': 10000, 'service_requests': []}, {'card_number': '3782-822463-10005', 'card_type': 'AMEX', 'status': 'ACTIVE', 'intl_usage': False, 'usage_limit': 0, 'current_balance': 0.0, 'annual_fee': 0.0, 'maximum_limit': 10000, 'service_requests': []}]}]","{'sql_query': \"SELECT T1.*, T2.*, T3.*\\nFROM   customers AS T1 LEFT JOIN cards AS T2 ON T1.customer_id = T2.customer_id LEFT JOIN service_requests AS T3 ON T2.card_number = T3.card_number\\nWHERE  T1.customer_id = :cid AND ( T3.status = 'pending' );\", 'sql_execution_response': '[{\"customer_id\": \"C003\", \"name\": \"Charlotte Lee\", \"phone\": \"+44-20-7946-0958\", \"region\": \"GB\", \"cards\": [{\"card_number\": \"6011-0009-9013-9424\", \"card_type\": \"DISCOVER\", \"status\": \"ACTIVE\", \"intl_usage\": true, \"usage_limit\": 2000, \"current_balance\": 1500.0, \"annual_fee\": 119.99, \"maximum_limit\": 10000, \"service_requests\": [{\"request_id\": 4, \"request_type\": \"CANCEL_CARD\", \"description\": \"No longer need secondary card; cancel please.\", \"status\": \"ACTIVE\"}]}]}]', 'db_call_needed': 'yes', 'sql_total_cost': '0.0009329'}"],["Do you guys charge an annual fee on my card? How much is it?","CHECK CARD ANNUAL FEE","1","yes","Incorrect match","SELECT T1.*, T2.* FROM customers AS T1 LEFT JOIN cards AS T2 ON T1.customer_id = T2.customer_id WHERE T1.customer_id = 'C015';","SELECT T1.*, T2.*\nFROM   customers AS T1 LEFT JOIN cards AS T2 ON T1.customer_id = T2.customer_id\nWHERE  T1.customer_id = :cid AND ( T2.annual_fee > 0 );","[]","[{'customer_id': 'C015', 'name': 'Olivia Brown', 'phone': '+44-20-7946-0123', 'region': 'GB', 'cards': [{'card_number': '5600-1111-2222-3333', 'card_type': 'VISA', 'status': 'ACTIVE', 'intl_usage': False, 'usage_limit': 0, 'current_balance': 0.0, 'annual_fee': 0.0, 'maximum_limit': 10000, 'service_requests': []}]}]","{'sql_query': 'SELECT T1.*, T2.*\\nFROM   customers AS T1 LEFT JOIN cards AS T2 ON T1.customer_id = T2.customer_id\\nWHERE  T1.customer_id = :cid AND ( T2.annual_fee > 0 );', 'sql_execution_response': '[]', 'db_call_needed': 'yes', 'sql_total_cost': '0.0008696'}"],["This is ridiculous, I paid my no-fee card and there's new charges \u00c3\u00a2\u00e2\u201a\u00ac\u00e2\u20ac\u009d pull up all transactions since that payment right now or I'm gonna be pissed.","CHECK CURRENT BALANCE ON CARD","1","no","No database call","SELECT T1.*, T2.* FROM customers AS T1 LEFT JOIN cards AS T2 ON T1.customer_id = T2.customer_id WHERE T1.customer_id = 'C010' AND ((T2.annual_fee = 0 OR T2.annual_fee IS NULL));","","[]","[{'customer_id': 'C010', 'name': 'Juan P\u00e9rez', 'phone': '+34-91-1234567', 'region': 'ES', 'cards': [{'card_number': '5100-1111-2222-3333', 'card_type': 'MC', 'status': 'BLOCKED', 'intl_usage': False, 'usage_limit': 0, 'current_balance': 0.0, 'annual_fee': 0.0, 'maximum_limit': 10000, 'service_requests': []}, {'card_number': '5100-4444-5555-6666', 'card_type': 'VISA', 'status': 'BLOCKED', 'intl_usage': False, 'usage_limit': 0, 'current_balance': 0.0, 'annual_fee': 0.0, 'maximum_limit': 10000, 'service_requests': []}]}]","{'sql_query': '', 'sql_execution_response': '[]', 'db_call_needed': 'no', 'sql_total_cost': '0.0007696000000000001'}"],["I've been going through my statements and I need you to tell me the balance on my last one, don't make me wait.","CHECK CURRENT BALANCE ON CARD","1","no","No database call","SELECT T1.*, T2.* FROM customers AS T1 LEFT JOIN cards AS T2 ON T1.customer_id = T2.customer_id WHERE T1.customer_id = 'C002';","","[]","[{'customer_id': 'C002', 'name': 'Bob Smith', 'phone': '+91-98765-43210', 'region': 'IN', 'cards': []}]","{'sql_query': '', 'sql_execution_response': '[]', 'db_call_needed': 'no', 'sql_total_cost': '0.0007660000000000001'}"],["Please send the transactions on my active card since my last payment right away.","CHECK CURRENT BALANCE ON CARD","1","no","No database call","SELECT T1.*, T2.* FROM customers AS T1 LEFT JOIN cards AS T2 ON T1.customer_id = T2.customer_id WHERE T1.customer_id = 'CUST1001' AND (LOWER(T2.status) = 'active');","","[]","[{'customer_id': 'CUST1001', 'name': 'Alice Smith', 'phone': '555-1234', 'region': 'NA', 'cards': [{'card_number': '1111-2222-3333-4444', 'card_type': 'Visa Debit', 'status': 'active', 'intl_usage': True, 'usage_limit': 5000, 'current_balance': 1500.75, 'annual_fee': 0.0, 'maximum_limit': 10000, 'service_requests': []}, {'card_number': '5555-6666-7777-8888', 'card_type': 'Mastercard Credit', 'status': 'active', 'intl_usage': False, 'usage_limit': 10000, 'current_balance': -250.5, 'annual_fee': 50.0, 'maximum_limit': 10000, 'service_requests': []}]}]","{'sql_query': '', 'sql_execution_response': '[]', 'db_call_needed': 'no', 'sql_total_cost': '0.0007618'}"],["Could you list my card transactions since my last bill for the card ending in 5500111122223333, please?","CHECK CURRENT BALANCE ON CARD","1","no","No database call","SELECT T1.*, T2.* FROM customers AS T1 LEFT JOIN cards AS T2 ON T1.customer_id = T2.customer_id WHERE T1.customer_id = 'C014' AND (REPLACE(T2.card_number, '-', '') = '5500111122223333');","","[]","[{'customer_id': 'C014', 'name': 'Nikolai Ivanov', 'phone': '+7-495-123-4567', 'region': 'RU', 'cards': [{'card_number': '5500-1111-2222-3333', 'card_type': 'MC', 'status': 'ACTIVE', 'intl_usage': True, 'usage_limit': 1000, 'current_balance': 600.0, 'annual_fee': 80.0, 'maximum_limit': 10000, 'service_requests': []}]}]","{'sql_query': '', 'sql_execution_response': '[]', 'db_call_needed': 'no', 'sql_total_cost': '0.0007678'}"],["I gotta see what I spent since I paid that bill, now.","CHECK CURRENT BALANCE ON CARD","1","no","No database call","SELECT T1.*, T2.* FROM customers AS T1 LEFT JOIN cards AS T2 ON T1.customer_id = T2.customer_id WHERE T1.customer_id = 'C013';","","[]","[{'customer_id': 'C013', 'name': 'Maria Silva', 'phone': '+55-11-91234-5678', 'region': 'BR', 'cards': [{'card_number': '5400-1111-2222-3333', 'card_type': 'VISA', 'status': 'ACTIVE', 'intl_usage': True, 'usage_limit': 300, 'current_balance': 150.0, 'annual_fee': 25.0, 'maximum_limit': 10000, 'service_requests': []}]}]","{'sql_query': '', 'sql_execution_response': '[]', 'db_call_needed': 'no', 'sql_total_cost': '0.0007615'}"],["I noticed some charges and I need to settle this today \u00c3\u00a2\u00e2\u201a\u00ac\u00e2\u20ac\u009d can you quickly tell me how much I've spent since my last card payment date? It's urgent, please.","CHECK CURRENT BALANCE ON CARD","1","no","No database call","SELECT T1.*, T2.* FROM customers AS T1 LEFT JOIN cards AS T2 ON T1.customer_id = T2.customer_id WHERE T1.customer_id = 'C013';","","[]","[{'customer_id': 'C013', 'name': 'Maria Silva', 'phone': '+55-11-91234-5678', 'region': 'BR', 'cards': [{'card_number': '5400-1111-2222-3333', 'card_type': 'VISA', 'status': 'ACTIVE', 'intl_usage': True, 'usage_limit': 300, 'current_balance': 150.0, 'annual_fee': 25.0, 'maximum_limit': 10000, 'service_requests': []}]}]","{'sql_query': '', 'sql_execution_response': '[]', 'db_call_needed': 'no', 'sql_total_cost': '0.0007702'}"],["I want a full breakdown of all transactions since my last payment date \u00c3\u00a2\u00e2\u201a\u00ac\u00e2\u20ac\u009d dates, merchants, amounts. Don't leave anything out.","CHECK CURRENT BALANCE ON CARD","1","no","No database call","SELECT T1.*, T2.* FROM customers AS T1 LEFT JOIN cards AS T2 ON T1.customer_id = T2.customer_id WHERE T1.customer_id = 'C007';","","[]","[{'customer_id': 'C007', 'name': 'Grace Chen', 'phone': '+86-10-12345678', 'region': 'CN', 'cards': [{'card_number': '3566-0020-2036-0505', 'card_type': 'JCB', 'status': 'ACTIVE', 'intl_usage': True, 'usage_limit': 500, 'current_balance': 50.0, 'annual_fee': 45.0, 'maximum_limit': 10000, 'service_requests': []}]}]","{'sql_query': '', 'sql_execution_response': '[]', 'db_call_needed': 'no', 'sql_total_cost': '0.0007672'}"],["Please, I paid my last bill few hours ago and I'm freaking out a bit\u00c3\u00a2\u00e2\u201a\u00ac\u00e2\u20ac\u009dcould you urgently please list every transaction that posted after that payment on the card ending 3530? Thanks.","CHECK CURRENT BALANCE ON CARD","1","yes","Incorrect match","SELECT T1.*, T2.* FROM customers AS T1 LEFT JOIN cards AS T2 ON T1.customer_id = T2.customer_id WHERE T1.customer_id = 'C006' AND (substr(REPLACE(T2.card_number, '-', ''), 1, 4) = '3530');","SELECT T1.*, T2.*\nFROM   customers AS T1 LEFT JOIN cards AS T2 ON T1.customer_id = T2.customer_id\nWHERE  T1.customer_id = :cid AND ( T2.card_number LIKE '%3530' );","[]","[{'customer_id': 'C006', 'name': 'Frank M\u00fcller', 'phone': '+49-30-123456', 'region': 'DE', 'cards': [{'card_number': '3530-1113-3330-0000', 'card_type': 'JCB', 'status': 'ACTIVE', 'intl_usage': False, 'usage_limit': 0, 'current_balance': 200.0, 'annual_fee': 75.0, 'maximum_limit': 10000, 'service_requests': []}]}]","{'sql_query': \"SELECT T1.*, T2.*\\nFROM   customers AS T1 LEFT JOIN cards AS T2 ON T1.customer_id = T2.customer_id\\nWHERE  T1.customer_id = :cid AND ( T2.card_number LIKE '%3530' );\", 'sql_execution_response': '[]', 'db_call_needed': 'yes', 'sql_total_cost': '0.000887'}"],["You need to tell me the last statement balance that's not paid for my active card, NOW \u00c3\u00a2\u00e2\u201a\u00ac\u00e2\u20ac\u009d I haven't time and this is ridiculous.","CHECK CURRENT BALANCE ON CARD","1","no","No database call","SELECT T1.*, T2.* FROM customers AS T1 LEFT JOIN cards AS T2 ON T1.customer_id = T2.customer_id WHERE T1.customer_id = 'CUST1001' AND (LOWER(T2.status) = 'active');","","[]","[{'customer_id': 'CUST1001', 'name': 'Alice Smith', 'phone': '555-1234', 'region': 'NA', 'cards': [{'card_number': '1111-2222-3333-4444', 'card_type': 'Visa Debit', 'status': 'active', 'intl_usage': True, 'usage_limit': 5000, 'current_balance': 1500.75, 'annual_fee': 0.0, 'maximum_limit': 10000, 'service_requests': []}, {'card_number': '5555-6666-7777-8888', 'card_type': 'Mastercard Credit', 'status': 'active', 'intl_usage': False, 'usage_limit': 10000, 'current_balance': -250.5, 'annual_fee': 50.0, 'maximum_limit': 10000, 'service_requests': []}]}]","{'sql_query': '', 'sql_execution_response': '[]', 'db_call_needed': 'no', 'sql_total_cost': '0.0007684'}"],["I lost my no annual fee card on my trip abroad, can you block it please","BLOCK CARD","1","yes","Incorrect match","SELECT T1.*, T2.* FROM customers AS T1 LEFT JOIN cards AS T2 ON T1.customer_id = T2.customer_id WHERE T1.customer_id = 'C005' AND ((T2.annual_fee = 0 OR T2.annual_fee IS NULL));","SELECT T1.*, T2.*\nFROM   customers AS T1 LEFT JOIN cards AS T2 ON T1.customer_id = T2.customer_id\nWHERE  T1.customer_id = :cid AND ( T2.annual_fee = 0 AND T2.intl_usage = 1 );","[]","[{'customer_id': 'C005', 'name': 'Evan Garc\u00eda', 'phone': '+1-305-555-0199', 'region': 'US', 'cards': [{'card_number': '6011-1111-1111-1117', 'card_type': 'DISCOVER', 'status': 'CANCELLED', 'intl_usage': False, 'usage_limit': 0, 'current_balance': 0.0, 'annual_fee': 0.0, 'maximum_limit': 10000, 'service_requests': []}]}]","{'sql_query': 'SELECT T1.*, T2.*\\nFROM   customers AS T1 LEFT JOIN cards AS T2 ON T1.customer_id = T2.customer_id\\nWHERE  T1.customer_id = :cid AND ( T2.annual_fee = 0 AND T2.intl_usage = 1 );', 'sql_execution_response': '[]', 'db_call_needed': 'yes', 'sql_total_cost': '0.0008948999999999999'}"],["My no-annual-fee card has been stolen and there are pending unauthorized charges \u00c3\u00a2\u00e2\u201a\u00ac\u00e2\u20ac\u009d block it immediately and do not authorize anything else, I need this sorted now.","BLOCK CARD","1","yes","Incorrect match","SELECT T1.*, T2.* FROM customers AS T1 LEFT JOIN cards AS T2 ON T1.customer_id = T2.customer_id WHERE T1.customer_id = 'C010' AND ((T2.annual_fee = 0 OR T2.annual_fee IS NULL));","SELECT T1.*, T2.*, T3.*\nFROM   customers AS T1 LEFT JOIN cards AS T2 ON T1.customer_id = T2.customer_id LEFT JOIN service_requests AS T3 ON T2.card_number = T3.card_number\nWHERE  T1.customer_id = :cid AND ( T2.annual_fee = 0 AND T3.status = 'pending' );","[{'customer_id': 'C010', 'name': 'Juan P\u00e9rez', 'phone': '+34-91-1234567', 'region': 'ES', 'cards': [{'card_number': '5100-1111-2222-3333', 'card_type': 'MC', 'status': 'BLOCKED', 'intl_usage': False, 'usage_limit': 0, 'current_balance': 0.0, 'annual_fee': 0.0, 'maximum_limit': 10000, 'service_requests': [{'request_id': 11, 'request_type': 'CANCEL_CARD', 'description': 'Two cards stolen; cancel both.', 'status': 'BLOCKED'}]}]}]","[{'customer_id': 'C010', 'name': 'Juan P\u00e9rez', 'phone': '+34-91-1234567', 'region': 'ES', 'cards': [{'card_number': '5100-1111-2222-3333', 'card_type': 'MC', 'status': 'BLOCKED', 'intl_usage': False, 'usage_limit': 0, 'current_balance': 0.0, 'annual_fee': 0.0, 'maximum_limit': 10000, 'service_requests': []}, {'card_number': '5100-4444-5555-6666', 'card_type': 'VISA', 'status': 'BLOCKED', 'intl_usage': False, 'usage_limit': 0, 'current_balance': 0.0, 'annual_fee': 0.0, 'maximum_limit': 10000, 'service_requests': []}]}]","{'sql_query': \"SELECT T1.*, T2.*, T3.*\\nFROM   customers AS T1 LEFT JOIN cards AS T2 ON T1.customer_id = T2.customer_id LEFT JOIN service_requests AS T3 ON T2.card_number = T3.card_number\\nWHERE  T1.customer_id = :cid AND ( T2.annual_fee = 0 AND T3.status = 'pending' );\", 'sql_execution_response': '[{\"customer_id\": \"C010\", \"name\": \"Juan P\\\\u00e9rez\", \"phone\": \"+34-91-1234567\", \"region\": \"ES\", \"cards\": [{\"card_number\": \"5100-1111-2222-3333\", \"card_type\": \"MC\", \"status\": \"BLOCKED\", \"intl_usage\": false, \"usage_limit\": 0, \"current_balance\": 0.0, \"annual_fee\": 0.0, \"maximum_limit\": 10000, \"service_requests\": [{\"request_id\": 11, \"request_type\": \"CANCEL_CARD\", \"description\": \"Two cards stolen; cancel both.\", \"status\": \"BLOCKED\"}]}]}]', 'db_call_needed': 'yes', 'sql_total_cost': '0.0009615'}"],["I was on my way home and think I left my card in a cab, can't find it anywhere and I'm really worried, could you block it straight away, I got off two stops ago and the driver was late so I dunno where it is now, last four 9876, thank you.","BLOCK CARD","1","yes","Incorrect match","SELECT T1.*, T2.* FROM customers AS T1 LEFT JOIN cards AS T2 ON T1.customer_id = T2.customer_id WHERE T1.customer_id = 'CUST1001' AND (LOWER(T2.status) = 'active');","SELECT T1.*, T2.*\nFROM   customers AS T1 LEFT JOIN cards AS T2 ON T1.customer_id = T2.customer_id\nWHERE  T1.customer_id = :cid AND ( T2.card_number LIKE '%9876' );","[]","[{'customer_id': 'CUST1001', 'name': 'Alice Smith', 'phone': '555-1234', 'region': 'NA', 'cards': [{'card_number': '1111-2222-3333-4444', 'card_type': 'Visa Debit', 'status': 'active', 'intl_usage': True, 'usage_limit': 5000, 'current_balance': 1500.75, 'annual_fee': 0.0, 'maximum_limit': 10000, 'service_requests': []}, {'card_number': '5555-6666-7777-8888', 'card_type': 'Mastercard Credit', 'status': 'active', 'intl_usage': False, 'usage_limit': 10000, 'current_balance': -250.5, 'annual_fee': 50.0, 'maximum_limit': 10000, 'service_requests': []}]}]","{'sql_query': \"SELECT T1.*, T2.*\\nFROM   customers AS T1 LEFT JOIN cards AS T2 ON T1.customer_id = T2.customer_id\\nWHERE  T1.customer_id = :cid AND ( T2.card_number LIKE '%9876' );\", 'sql_execution_response': '[]', 'db_call_needed': 'yes', 'sql_total_cost': '0.0008921000000000001'}"],["Fraudulent charges \u00c3\u00a2\u00e2\u201a\u00ac\u00e2\u20ac\u009d block my card immediately, this is outrageous.","BLOCK CARD","1","yes","Incorrect match","SELECT T1.*, T2.* FROM customers AS T1 LEFT JOIN cards AS T2 ON T1.customer_id = T2.customer_id WHERE T1.customer_id = 'C011';","SELECT T1.*, T2.*, T3.*\nFROM   customers AS T1 LEFT JOIN cards AS T2 ON T1.customer_id = T2.customer_id LEFT JOIN service_requests AS T3 ON T2.card_number = T3.card_number\nWHERE  T1.customer_id = :cid AND ( LOWER(T3.request_type) LIKE '%block card%' AND T3.status = 'pending' );","[]","[{'customer_id': 'C011', 'name': 'Keiko Tanaka', 'phone': '+81-3-1234-5678', 'region': 'JP', 'cards': [{'card_number': '5200-1111-2222-3333', 'card_type': 'VISA', 'status': 'ACTIVE', 'intl_usage': True, 'usage_limit': 5000, 'current_balance': 2000.0, 'annual_fee': 150.0, 'maximum_limit': 10000, 'service_requests': []}]}]","{'sql_query': \"SELECT T1.*, T2.*, T3.*\\nFROM   customers AS T1 LEFT JOIN cards AS T2 ON T1.customer_id = T2.customer_id LEFT JOIN service_requests AS T3 ON T2.card_number = T3.card_number\\nWHERE  T1.customer_id = :cid AND ( LOWER(T3.request_type) LIKE '%block card%' AND T3.status = 'pending' );\", 'sql_execution_response': '[]', 'db_call_needed': 'yes', 'sql_total_cost': '0.0009705'}"]]}