{"data":[{"fill":"toself","legendgroup":"SFR-Embedding-Mistral","name":"SFR-Embedding-Mistral","r":[0.93,0.69,0.58,0.67,0.72,0.87],"theta":["Cosine Similarity","L2 distance","Inner product\u002fdot product","L2-Squared-distance","Hamming distance","Manhattan distance"],"type":"scatterpolar"},{"fill":"toself","legendgroup":"Voyage-lite-02-instruct","name":"Voyage-lite-02-instruct","r":[0.9,0.38,0.36,0.4,0.63,0.8],"theta":["Cosine Similarity","L2 distance","Inner product\u002fdot product","L2-Squared-distance","Hamming distance","Manhattan distance"],"type":"scatterpolar"},{"fill":"toself","legendgroup":"text-embedding-3-large","name":"text-embedding-3-large","r":[0.52,0.26,0.34,0.3,0.27,0.6],"theta":["Cosine Similarity","L2 distance","Inner product\u002fdot product","L2-Squared-distance","Hamming distance","Manhattan distance"],"type":"scatterpolar"},{"fill":"toself","legendgroup":"gte-base","name":"gte-base","r":[0.74,0.38,0.51,0.5,0.5,0.7],"theta":["Cosine Similarity","L2 distance","Inner product\u002fdot product","L2-Squared-distance","Hamming distance","Manhattan distance"],"type":"scatterpolar"},{"fill":"toself","legendgroup":"sentence-t5-xl","name":"sentence-t5-xl","r":[0.55,0.35,0.42,0.48,0.56,0.42],"theta":["Cosine Similarity","L2 distance","Inner product\u002fdot product","L2-Squared-distance","Hamming distance","Manhattan distance"],"type":"scatterpolar"}],"layout":{"template":{"data":{"table":[{"cells":{"align":"left","fill":{"color":"#fff"},"font":{"color":"#2D3138","size":12},"height":30,"line":{"color":"#DDDFE1","width":0.5}},"columnwidth":0.5,"header":{"align":"left","fill":{"color":"#f1f1f1"},"font":{"color":"#2D3138","size":14},"line":{"color":"#DDDFE1","width":1}},"type":"table"}]},"layout":{"colorway":["#1aaeba","#f5b225","#3E9651","#6B4C9A","#535154","#948B3D"],"font":{"family":"Open Sans"},"height":450,"margin":{"autoexpand":true,"b":50,"t":60},"title":{"font":{"color":"#2D3138","family":"Open Sans","size":18}},"updatemenudefaults":{"active":0,"pad":{"r":10,"t":15},"showactive":true,"x":1,"xanchor":"left","y":1.2,"yanchor":"top"},"xaxis":{"automargin":true,"rangeslider":{"visible":true},"showline":true,"zeroline":false},"yaxis":{"automargin":true,"showline":true,"zeroline":false}}},"title":{"text":"Performance of different Embedding Techniques","x":0.5},"polar":{"radialaxis":{"visible":true,"range":[0,1]}},"showlegend":true}}